{
  "title" : "Simple test survey",
  "fields" : [ {
    "type" : "freetext",
    "id" : "qName",
    "hidden" : false,
    "question" : "What is your name?",
    "optional" : false,
    "length" : "SHORT"
  }, {
    "type" : "singlechoice",
    "id" : "qHappy",
    "hidden" : false,
    "question" : "Are you happy?",
    "optional" : false,
    "choices" : [ {
      "name" : "Yes"
    }, {
      "name" : "No"
    } ],
    "allowOther" : false
  }, {
    "type" : "instruction",
    "id" : "iGood",
    "hidden" : false,
    "text" : "Good for you!"
  }, {
    "type" : "scale",
    "id" : "qBadScale",
    "hidden" : false,
    "question" : "Oh no! How bad are things?",
    "optional" : false,
    "scaleType" : "star",
    "length" : 5,
    "descriptions" : [ "Not that bad", "Pretty bad", "Horrible", "Terrible", "Catastrophic" ]
  }, {
    "type" : "freetext",
    "id" : "qBadReason",
    "hidden" : false,
    "question" : "Oh man! That sounds really bad. How come?",
    "optional" : false,
    "length" : "LONG"
  } ],
  "fieldRules" : [ {
    "trigger" : {
      "questionId" : "qHappy",
      "condition" : "is",
      "choice" : "Yes"
    },
    "actions" : [ {
      "action" : "show",
      "fieldId" : "iGood"
    } ]
  }, {
    "trigger" : {
      "questionId" : "qHappy",
      "condition" : "is",
      "choice" : "No"
    },
    "actions" : [ {
      "action" : "show",
      "fieldId" : "qBadScale"
    } ]
  }, {
    "trigger" : {
      "questionId" : "qBadScale",
      "condition" : "greaterThan",
      "index" : 2
    },
    "actions" : [ {
      "action" : "show",
      "fieldId" : "qBadReason"
    } ]
  } ],
  "pageRules" : [ ],
  "createdAt" : 1427170151014,
  "modifiedAt" : 1427170151027,
  "finalized" : false,
  "deleted" : false
}